MANIFEST.in
PyCrypterFUD.py
setup.py
ceshigogogo1/__init__.py
ceshigogogo1.egg-info/PKG-INFO
ceshigogogo1.egg-info/SOURCES.txt
ceshigogogo1.egg-info/dependency_links.txt
ceshigogogo1.egg-info/requires.txt
ceshigogogo1.egg-info/top_level.txt