Metadata-Version: 2.2
Name: ceshigogogo1
Version: 0.2
Requires-Dist: requests>=2.25.1
Dynamic: requires-dist
